PartyBot/__init__.py
PartyBot-0.0.1.dist-info/METADATA
PartyBot-0.0.1.dist-info/WHEEL
PartyBot-0.0.1.dist-info/top_level.txt
PartyBot-0.0.1.dist-info/RECORD
