Metadata-Version: 2.1
Name: PartyBot
Version: 0.0.1
Summary: A Multi Action Fortnite Bot
Home-page: https://partybot.net
Author: Pirxcy
License: UNKNOWN
Platform: UNKNOWN
Classifier: Programming Language :: Python :: 3
Classifier: License :: OSI Approved :: MIT License
Classifier: Operating System :: OS Independent
Requires-Dist: sanic
Requires-Dist: crayons
Requires-Dist: pycld2
Requires-Dist: fortnite-api
Requires-Dist: requests
Requires-Dist: jinja2
Requires-Dist: jaconv
Requires-Dist: colorama
Requires-Dist: fortnitepy
Requires-Dist: BenBotAsync
Requires-Dist: aioconsole
Requires-Dist: FortniteAPIAsync
